practable/__init__.py
practable/core.py
practable-0.0.25.dist-info/METADATA
practable-0.0.25.dist-info/WHEEL
practable-0.0.25.dist-info/licenses/LICENSE
practable-0.0.25.dist-info/RECORD
