Metadata-Version: 2.3
Name: practable
Version: 0.0.25
Summary: Connect to remote laboratory experiments hosted on a github.com/practable service
Project-URL: Homepage, https://github.com/practable/practable-python
Project-URL: Issues, https://github.com/practable/practable-python/issues
Author-email: Timothy Drysdale <timothy.d.drysdale@gmail.com>
License-File: LICENSE
Classifier: License :: OSI Approved :: GNU Affero General Public License v3
Classifier: Operating System :: OS Independent
Classifier: Programming Language :: Python :: 3
Requires-Python: >=3.8
Requires-Dist: platformdirs>=4.2
Requires-Dist: requests>=2.32
Requires-Dist: websockets>=12.0
